MANIFEST.in
README.md
pyproject.toml
setup.py
ibmcloudsql/SQLQuery.py
ibmcloudsql/__init__.py
ibmcloudsql/catalog_table.py
ibmcloudsql/cos.py
ibmcloudsql/exceptions.py
ibmcloudsql/sql_magic.py
ibmcloudsql/sql_query_ts.py
ibmcloudsql/test.py
ibmcloudsql/test_credentials.py
ibmcloudsql/utilities.py
ibmcloudsql.egg-info/PKG-INFO
ibmcloudsql.egg-info/SOURCES.txt
ibmcloudsql.egg-info/dependency_links.txt
ibmcloudsql.egg-info/requires.txt
ibmcloudsql.egg-info/top_level.txt
tests/test_cos.py
tests/test_sql_magic.py
tests/test_sqlquery.py