Metadata-Version: 2.1
Name: ibmcloudsql
Version: 0.5.14
Summary: Python client for interacting with IBM Cloud Data Engine service
Home-page: https://github.com/IBM-Cloud/sql-query-clients
Author: IBM Corp.
Author-email: torsten@de.ibm.com
License: Apache 2.0
Keywords: sql cloud object_storage IBM
Classifier: Development Status :: 4 - Beta
Classifier: License :: OSI Approved :: Apache Software License
Classifier: Programming Language :: Python :: 3.8
Classifier: Topic :: Database
Requires-Python: >=3.8, <4
Requires-Dist: pandas>=1.1.0
Requires-Dist: requests>=2.2.0
Requires-Dist: ibm-cos-sdk-core>=2.10.0
Requires-Dist: ibm-cos-sdk>=2.10.0
Requires-Dist: numpy>=1.20.3
Requires-Dist: pyarrow
Requires-Dist: backoff==1.10.0
Requires-Dist: sqlparse>=0.4.2
Requires-Dist: packaging
Requires-Dist: pre-commit
Requires-Dist: isodate
Requires-Dist: importlib-metadata
Requires-Dist: typing-extensions
Requires-Dist: python-dateutil
Requires-Dist: deprecated
